eanalizer/__init__.py
eanalizer/cli.py
eanalizer/config.py
eanalizer/core.py
eanalizer/data_loader.py
eanalizer/downloader.py
eanalizer/downloader_cli.py
eanalizer/models.py
eanalizer/price_fetcher.py
eanalizer/tariffs.py
eanalizer-0.3.4.dist-info/licenses/LICENSE
eanalizer-0.3.4.dist-info/METADATA
eanalizer-0.3.4.dist-info/WHEEL
eanalizer-0.3.4.dist-info/entry_points.txt
eanalizer-0.3.4.dist-info/top_level.txt
eanalizer-0.3.4.dist-info/RECORD
