Metadata-Version: 2.4
Name: eanalizer
Version: 0.3.4
Summary: Aplikacja do analizy zużycia energii elektrycznej z danych od operatorów (Enea, Tauron).
Author: TheUndefined
License: GPL-3.0-or-later
Project-URL: Homepage, https://github.com/theundefined/eanalizer
Project-URL: Bug Tracker, https://github.com/theundefined/eanalizer/issues
Keywords: enea,energy,analiza,fotowoltaika,tauron
Classifier: Development Status :: 3 - Alpha
Classifier: Environment :: Console
Classifier: Intended Audience :: End Users/Desktop
Classifier: License :: OSI Approved :: MIT License
Classifier: Programming Language :: Python :: 3
Classifier: Programming Language :: Python :: 3.8
Classifier: Programming Language :: Python :: 3.9
Classifier: Programming Language :: Python :: 3.10
Classifier: Programming Language :: Python :: 3.11
Classifier: Programming Language :: Python :: 3.12
Classifier: Topic :: Utilities
Requires-Python: >=3.8
License-File: LICENSE
Requires-Dist: pandas>=2.0.0
Requires-Dist: openpyxl>=3.0.0
Requires-Dist: holidays>=0.40
Requires-Dist: platformdirs>=4.0.0
Requires-Dist: requests>=2.30.0
Provides-Extra: dev
Requires-Dist: Babel; extra == "dev"
Dynamic: license-file
